XeLib/__init__.py
XeLib/cls.py
XeLib/color.py
XeLib/downloader.py
XeLib/getmyping.py
XeLib/isinternet.py
XeLib/mbgb.py
XeLib/printer.py
XeLib-1.0.dist-info/METADATA
XeLib-1.0.dist-info/WHEEL
XeLib-1.0.dist-info/top_level.txt
XeLib-1.0.dist-info/RECORD
